schleppy/__init__.py
schleppy/json_utils.py
schleppy/reach.py
schleppy/string_utils.py
schleppy/transform.py
schleppy-1.1.22.dist-info/LICENSE
schleppy-1.1.22.dist-info/METADATA
schleppy-1.1.22.dist-info/WHEEL
schleppy-1.1.22.dist-info/top_level.txt
schleppy-1.1.22.dist-info/RECORD
