Metadata-Version: 2.1
Name: schleppy
Version: 1.1.22
Summary: Utilities for traversing and transforming data structures
Home-page: http://github.com/bradodarb/schleppy
Author: Brad Murry
Author-email: bradodarb@hotmail.com
License: MIT
Keywords: dict list path dot notation
Platform: UNKNOWN
Classifier: License :: OSI Approved :: MIT License
Classifier: Programming Language :: Python :: 3
